[{"name":"SHY Martin - Out of My Hands (Lyrics)","track":"/music/","data":{"type":"video","videoId":"5mWhiLS1XJE","url":"https://youtube.com/watch?v=5mWhiLS1XJE","title":"SHY Martin - Out of My Hands (Lyrics)","description":"tags: #shymartin #outofmyhands #lyrics #lyric #lyricsvideo #lyricvideo #audio #newmelody #shy #martin For submissions, ...","image":"https://i.ytimg.com/vi/5mWhiLS1XJE/hq720.jpg","thumbnail":"https://i.ytimg.com/vi/5mWhiLS1XJE/hq720.jpg","seconds":204,"timestamp":"3:24","duration":{"seconds":204,"timestamp":"3:24"},"ago":"3 years ago","views":2967802,"author":{"name":"NewMelody","url":"https://youtube.com/c/NewMelody"}}},{"name":"Rick Astley - Never Gonna Give You Up (Official Music Video)","track":"/music/","data":{"type":"video","videoId":"dQw4w9WgXcQ","url":"https://youtube.com/watch?v=dQw4w9WgXcQ","title":"Rick Astley - Never Gonna Give You Up (Official Music Video)","description":"“Never Gonna Give You Up” was a global smash on its release in July 1987, topping the charts in 25 countries including Rick's ...","image":"https://i.ytimg.com/vi/dQw4w9WgXcQ/hq720.jpg","thumbnail":"https://i.ytimg.com/vi/dQw4w9WgXcQ/hq720.jpg","seconds":213,"timestamp":"3:33","duration":{"seconds":213,"timestamp":"3:33"},"ago":"12 years ago","views":1303673173,"author":{"name":"Rick Astley","url":"https://youtube.com/channel/UCuAXFkgsw1L7xaCfnd5JJOw"}}},{"name":"8 Letters - Why Don't We [Official Music Video]","track":"/music/","data":{"type":"video","videoId":"C3DlM19x4RQ","url":"https://youtube.com/watch?v=C3DlM19x4RQ","title":"8 Letters - Why Don't We [Official Music Video]","description":"TEXT US: +1 (323) 348-1663.","image":"https://i.ytimg.com/vi/C3DlM19x4RQ/hq720.jpg","thumbnail":"https://i.ytimg.com/vi/C3DlM19x4RQ/hq720.jpg","seconds":192,"timestamp":"3:12","duration":{"seconds":192,"timestamp":"3:12"},"ago":"4 years ago","views":103020272,"author":{"name":"Why Don't We","url":"https://youtube.com/channel/UCgJMQU7JOIoP-YnrhH_P-bA"}}}]